TelegramApiClient/__init__.py
TelegramApiClient-0.72.dist-info/LICENSE
TelegramApiClient-0.72.dist-info/METADATA
TelegramApiClient-0.72.dist-info/WHEEL
TelegramApiClient-0.72.dist-info/top_level.txt
TelegramApiClient-0.72.dist-info/RECORD
